{
  "_fv": 47,
  "_type": "gui",
  "definition": {
    "type": 1,
    "width": 500,
    "height": 500,
    "inventoryOffsetX": 0,
    "inventoryOffsetY": 40,
    "renderBgLayer": true,
    "doesPauseGame": false,
    "components": [
      {
        "type": "textfield",
        "data": {
          "placeholder": "Name..",
          "name": "SwordName",
          "width": 120,
          "height": 20,
          "x": 153,
          "y": 101
        }
      },
      {
        "type": "label",
        "data": {
          "name": "label_weapon_types",
          "text": {
            "fixedValue": "Weapon Types"
          },
          "color": {
            "value": -12829636,
            "falpha": 0.0
          },
          "x": 22,
          "y": 15
        }
      },
      {
        "type": "button",
        "data": {
          "name": "button_create",
          "text": "Create",
          "onClick": {
            "name": "CreatePressed"
          },
          "width": 56,
          "height": 20,
          "x": 185,
          "y": 123
        }
      },
      {
        "type": "inputslot",
        "data": {
          "inputLimit": {
            "value": "Items.IRON_INGOT"
          },
          "disablePlacement": {
            "fixedValue": false
          },
          "id": 0,
          "disablePickup": {
            "fixedValue": false
          },
          "dropItemsWhenNotBound": true,
          "x": 321,
          "y": 35
        }
      },
      {
        "type": "inputslot",
        "data": {
          "inputLimit": {
            "value": "Items.DIAMOND"
          },
          "disablePlacement": {
            "fixedValue": false
          },
          "id": 1,
          "disablePickup": {
            "fixedValue": false
          },
          "dropItemsWhenNotBound": true,
          "x": 321,
          "y": 62
        }
      },
      {
        "type": "inputslot",
        "data": {
          "inputLimit": {
            "value": "Blocks.DIAMOND_BLOCK"
          },
          "disablePlacement": {
            "fixedValue": false
          },
          "id": 2,
          "disablePickup": {
            "fixedValue": false
          },
          "dropItemsWhenNotBound": true,
          "x": 321,
          "y": 89
        }
      },
      {
        "type": "label",
        "data": {
          "name": "label_materials",
          "text": {
            "fixedValue": "Materials"
          },
          "color": {
            "value": -12829636,
            "falpha": 0.0
          },
          "x": 344,
          "y": 14
        }
      },
      {
        "type": "label",
        "data": {
          "name": "label_cots",
          "text": {
            "fixedValue": "Cots",
            "name": "DisplayCost"
          },
          "color": {
            "value": -12829636,
            "falpha": 0.0
          },
          "x": 191,
          "y": 147
        }
      },
      {
        "type": "label",
        "data": {
          "name": "label_5_cost",
          "text": {
            "fixedValue": "+5 Cost"
          },
          "color": {
            "value": -12829636,
            "falpha": 0.0
          },
          "x": 92,
          "y": 40
        }
      },
      {
        "type": "label",
        "data": {
          "name": "label_3_cost",
          "text": {
            "fixedValue": "+3 Cost"
          },
          "color": {
            "value": -12829636,
            "falpha": 0.0
          },
          "x": 70,
          "y": 76
        }
      },
      {
        "type": "label",
        "data": {
          "name": "label_1_cost",
          "text": {
            "fixedValue": "+1 Cost"
          },
          "color": {
            "value": -12829636,
            "falpha": 0.0
          },
          "x": 71,
          "y": 113
        }
      },
      {
        "type": "checkbox",
        "data": {
          "name": "KatanaBox",
          "text": "Katana",
          "x": 5,
          "y": 70
        }
      },
      {
        "type": "checkbox",
        "data": {
          "name": "GreatswordBox",
          "text": "Greatsword",
          "x": 5,
          "y": 34
        }
      },
      {
        "type": "checkbox",
        "data": {
          "name": "DaggerBox",
          "text": "Dagger",
          "x": 5,
          "y": 107
        }
      },
      {
        "type": "label",
        "data": {
          "name": "label_errormessage",
          "text": {
            "fixedValue": "ErrorMessage",
            "name": "DIsplayError"
          },
          "color": {
            "value": -65536,
            "falpha": 0.0
          },
          "displayCondition": {
            "name": "DIsplayV"
          },
          "x": 153,
          "y": 89
        }
      },
      {
        "type": "label",
        "data": {
          "name": "label_iron_ingots",
          "text": {
            "fixedValue": "Iron Ingots"
          },
          "color": {
            "value": -12829636,
            "falpha": 0.0
          },
          "x": 346,
          "y": 39
        }
      },
      {
        "type": "label",
        "data": {
          "name": "label_diamonds",
          "text": {
            "fixedValue": "Diamonds"
          },
          "color": {
            "value": -12829636,
            "falpha": 0.0
          },
          "x": 347,
          "y": 66
        }
      },
      {
        "type": "label",
        "data": {
          "name": "label_diamond_blocks",
          "text": {
            "fixedValue": "Diamond Blocks"
          },
          "color": {
            "value": -12829636,
            "falpha": 0.0
          },
          "x": 347,
          "y": 93
        }
      },
      {
        "type": "label",
        "data": {
          "name": "label_cursed_energy_investment",
          "text": {
            "fixedValue": "Cursed Energy Investment"
          },
          "color": {
            "value": -12829636,
            "falpha": 0.0
          },
          "x": 148,
          "y": 15
        }
      },
      {
        "type": "button",
        "data": {
          "name": "button_empty",
          "text": "+",
          "onClick": {
            "name": "PlusPressed"
          },
          "width": 30,
          "height": 20,
          "x": 246,
          "y": 33
        }
      },
      {
        "type": "button",
        "data": {
          "name": "button_empty1",
          "text": "-",
          "onClick": {
            "name": "PressedMinus"
          },
          "width": 30,
          "height": 20,
          "x": 151,
          "y": 33
        }
      },
      {
        "type": "label",
        "data": {
          "name": "label_amount",
          "text": {
            "fixedValue": "Amount",
            "name": "DisplayAmount"
          },
          "color": {
            "value": -12829636,
            "falpha": 0.0
          },
          "x": 205,
          "y": 38
        }
      }
    ],
    "gridSettings": {
      "sx": 18,
      "sy": 18,
      "ox": 11,
      "oy": 15,
      "snapOnGrid": false
    }
  }
}